torch_activation/__init__.py
torch_activation/adaptive/__init__.py
torch_activation/adaptive/abu.py
torch_activation/adaptive/faaf.py
torch_activation/adaptive/laaf.py
torch_activation/adaptive/melu.py
torch_activation/adaptive/msrf.py
torch_activation/adaptive/relu.py
torch_activation/adaptive/s_shaped.py
torch_activation/adaptive/sigmoid.py
torch_activation/adaptive/sigmoid_weighted.py
torch_activation/base.py
torch_activation/classical/__init__.py
torch_activation/classical/caf.py
torch_activation/classical/etanh.py
torch_activation/classical/exp.py
torch_activation/classical/glu.py
torch_activation/classical/layer.py
torch_activation/classical/maxsig.py
torch_activation/classical/other.py
torch_activation/classical/piecewise.py
torch_activation/classical/polynomial.py
torch_activation/classical/relu.py
torch_activation/classical/sigmoid.py
torch_activation/classical/sigmoid_weighted.py
torch_activation/classical/softmax.py
torch_activation/classical/softplus.py
torch_activation/classical/sqrt.py
torch_activation/classical/squared.py
torch_activation/classical/trig.py
torch_activation/utils.py
torch_activation-0.4.0.dist-info/LICENSE
torch_activation-0.4.0.dist-info/METADATA
torch_activation-0.4.0.dist-info/WHEEL
torch_activation-0.4.0.dist-info/RECORD
