Metadata-Version: 2.3
Name: torch-activation
Version: 0.4.0
Summary: A library of new activation function implement in PyTorch to save time in experiment and have fun
License: MIT
Author: Alan Huynh
Author-email: hdmquan@outlook.com
Requires-Python: >=3.10,<4.0
Classifier: License :: OSI Approved :: MIT License
Classifier: Programming Language :: Python :: 3
Classifier: Programming Language :: Python :: 3.10
Classifier: Programming Language :: Python :: 3.11
Classifier: Programming Language :: Python :: 3.12
Classifier: Programming Language :: Python :: 3.13
Requires-Dist: kaleido (==0.2)
Requires-Dist: loguru (>=0.7.3,<0.8.0)
Requires-Dist: plotly (>=6.0.0,<7.0.0)
Requires-Dist: pytest (>=8.3.5,<9.0.0)
Requires-Dist: scipy (>=1.15.2,<2.0.0)
Requires-Dist: sphinx (==8.0)
Requires-Dist: torch (>=1.13.0)
